{
    "type": "FeatureCollection",
    "features": [
      {
        "type": "Feature",
        "properties": {
          "name": "United States"
        },
        "geometry": {
          "type": "Polygon",
          "coordinates": [
            [
              [-171.791110603, 18.91348],
              [-66.93457, 18.91348],
              [-66.93457, 49.58712],
              [-171.791110603, 49.58712],
              [-171.791110603, 18.91348]
            ]
          ]
        }
      },
      {
        "type": "Feature",
        "properties": {
          "name": "Canada"
        },
        "geometry": {
          "type": "Polygon",
          "coordinates": [
            [
              [-141.00187, 41.67682],
              [-52.6176, 41.67682],
              [-52.6176, 83.23324],
              [-141.00187, 83.23324],
              [-141.00187, 41.67682]
            ]
          ]
        }
      },
      {
        "type": "Feature",
        "properties": {
          "name": "Brazil"
        },
        "geometry": {
          "type": "Polygon",
          "coordinates": [
            [
              [-73.9875, -33.7681],
              [-33.7681, -33.7681],
              [-33.7681, 5.2645],
              [-73.9875, 5.2645],
              [-73.9875, -33.7681]
            ]
          ]
        }
      },
      {
        "type": "Feature",
        "properties": {
          "name": "Australia"
        },
        "geometry": {
          "type": "Polygon",
          "coordinates": [
            [
              [112.9211, -44.0145],
              [159.089, -44.0145],
              [159.089, -10.6682],
              [112.9211, -10.6682],
              [112.9211, -44.0145]
            ]
          ]
        }
      },
      {
        "type": "Feature",
        "properties": {
          "name": "China"
        },
        "geometry": {
          "type": "Polygon",
          "coordinates": [
            [
              [73.6754, 18.1977],
              [134.7739, 18.1977],
              [134.7739, 53.5608],
              [73.6754, 53.5608],
              [73.6754, 18.1977]
            ]
          ]
        }
      }
    ]
  }
  